README.md
setup.py
nivir/__init__.py
nivir/main.py
nivir/model.py
nivir/window.py
nivir.egg-info/PKG-INFO
nivir.egg-info/SOURCES.txt
nivir.egg-info/dependency_links.txt
nivir.egg-info/top_level.txt